icexmoon__hello_world/__init__.py
icexmoon__hello_world/__main__.py
icexmoon_hello_world-0.1.5.dist-info/METADATA
icexmoon_hello_world-0.1.5.dist-info/WHEEL
icexmoon_hello_world-0.1.5.dist-info/entry_points.txt
icexmoon_hello_world-0.1.5.dist-info/top_level.txt
icexmoon_hello_world-0.1.5.dist-info/RECORD
