Metadata-Version: 2.4
Name: icexmoon-hello-world
Version: 0.1.5
Summary: Add your description here
Requires-Python: >=3.13
Requires-Dist: requests==2.31.0
Requires-Dist: rich>=14.1.0
